antodo/__init__.py
antodo/config.py
antodo/todo.py
antodo/todo_cli.py
antodo/todo_editor.py
antodo/todos.py
antodo/todos_loader.py
antodo-0.6.0.dist-info/entry_points.txt
antodo-0.6.0.dist-info/WHEEL
antodo-0.6.0.dist-info/METADATA
antodo-0.6.0.dist-info/RECORD
